aiovlc/__init__.py
aiovlc/__main__.py
aiovlc/cli.py
aiovlc/client.py
aiovlc/const.py
aiovlc/exceptions.py
aiovlc/model/__init__.py
aiovlc/model/command.py
aiovlc/py.typed
aiovlc-0.6.5.dist-info/LICENSE
aiovlc-0.6.5.dist-info/METADATA
aiovlc-0.6.5.dist-info/WHEEL
aiovlc-0.6.5.dist-info/entry_points.txt
aiovlc-0.6.5.dist-info/RECORD
