Metadata-Version: 2.1
Name: aiovlc
Version: 0.6.5
Summary: Control VLC over telnet connection using asyncio
Home-page: https://github.com/MartinHjelmare/aiovlc
License: Apache-2.0
Author: Martin Hjelmare
Author-email: marhje52@gmail.com
Requires-Python: >=3.11,<4.0
Classifier: Development Status :: 3 - Alpha
Classifier: Intended Audience :: Developers
Classifier: License :: OSI Approved :: Apache Software License
Classifier: Natural Language :: English
Classifier: Operating System :: OS Independent
Classifier: Programming Language :: Python :: 3
Classifier: Programming Language :: Python :: 3.11
Classifier: Programming Language :: Python :: 3.12
Classifier: Programming Language :: Python :: 3.13
Classifier: Topic :: Software Development :: Libraries
Provides-Extra: cli
Requires-Dist: typer (>=0.15.0,<0.16.0) ; extra == "cli"
Project-URL: Bug Tracker, https://github.com/MartinHjelmare/aiovlc/issues
Project-URL: Changelog, https://github.com/MartinHjelmare/aiovlc/blob/main/CHANGELOG.md
Project-URL: Documentation, https://aiovlc.readthedocs.io
Project-URL: Repository, https://github.com/MartinHjelmare/aiovlc
